gc_bokeh_app_test/__init__.py
gc_bokeh_app_test/myapp.py
gc_bokeh_app_test/myappruns.py
gc_bokeh_app_test/runserver.py
gc_bokeh_app_test-0.0.3.dist-info/METADATA
gc_bokeh_app_test-0.0.3.dist-info/WHEEL
gc_bokeh_app_test-0.0.3.dist-info/top_level.txt
gc_bokeh_app_test-0.0.3.dist-info/RECORD
